libwine/__init__.py
libwine/exceptions.py
libwine/proton.py
libwine/wine.py
libwine/wineprocess.py
libwine/utils/__init__.py
libwine/utils/command.py
libwine-0.5.dist-info/LICENSE
libwine-0.5.dist-info/METADATA
libwine-0.5.dist-info/WHEEL
libwine-0.5.dist-info/top_level.txt
libwine-0.5.dist-info/RECORD
