Metadata-Version: 2.1
Name: libwine
Version: 0.5
Summary: A python library for interacting with Wine.
Home-page: https://github.com/bottlesdevs/libwine
Author: Mirko Brombin
Author-email: send@mirko.pm
License: GPL-3.0
Project-URL: Bug Tracker, https://github.com/bottlesdevs/libwine/issues
Keywords: libwine wine proton windows
Platform: UNKNOWN
Classifier: Programming Language :: Python :: 3
Classifier: License :: OSI Approved :: GNU General Public License v3 (GPLv3)
Classifier: Operating System :: POSIX :: Linux
Requires-Python: >=3.6
